lckr_jupyterlab_variableinspector/__init__.py
lckr_jupyterlab_variableinspector/_version.py
lckr_jupyterlab_variableinspector-3.2.4.data/data/share/jupyter/labextensions/@lckr/jupyterlab_variableinspector/package.json
lckr_jupyterlab_variableinspector-3.2.4.data/data/share/jupyter/labextensions/@lckr/jupyterlab_variableinspector/schemas/@lckr/jupyterlab_variableinspector/jupyterlab-variableInspector-settings.json
lckr_jupyterlab_variableinspector-3.2.4.data/data/share/jupyter/labextensions/@lckr/jupyterlab_variableinspector/schemas/@lckr/jupyterlab_variableinspector/package.json.orig
lckr_jupyterlab_variableinspector-3.2.4.data/data/share/jupyter/labextensions/@lckr/jupyterlab_variableinspector/static/377.a6995c94796dd012b2e6.js
lckr_jupyterlab_variableinspector-3.2.4.data/data/share/jupyter/labextensions/@lckr/jupyterlab_variableinspector/static/455.0b2acec0b13b6320f36a.js
lckr_jupyterlab_variableinspector-3.2.4.data/data/share/jupyter/labextensions/@lckr/jupyterlab_variableinspector/static/498.9433196881674d20b32e.js
lckr_jupyterlab_variableinspector-3.2.4.data/data/share/jupyter/labextensions/@lckr/jupyterlab_variableinspector/static/50.8aba103854790d4ac3ef.js
lckr_jupyterlab_variableinspector-3.2.4.data/data/share/jupyter/labextensions/@lckr/jupyterlab_variableinspector/static/590.66f87d59f52e29c76e04.js
lckr_jupyterlab_variableinspector-3.2.4.data/data/share/jupyter/labextensions/@lckr/jupyterlab_variableinspector/static/728.f1a164cd599fe2e035eb.js
lckr_jupyterlab_variableinspector-3.2.4.data/data/share/jupyter/labextensions/@lckr/jupyterlab_variableinspector/static/90.07c408766933e85c9db6.js
lckr_jupyterlab_variableinspector-3.2.4.data/data/share/jupyter/labextensions/@lckr/jupyterlab_variableinspector/static/90.07c408766933e85c9db6.js.LICENSE.txt
lckr_jupyterlab_variableinspector-3.2.4.data/data/share/jupyter/labextensions/@lckr/jupyterlab_variableinspector/static/remoteEntry.f4a64e687ab347206c17.js
lckr_jupyterlab_variableinspector-3.2.4.dist-info/METADATA
lckr_jupyterlab_variableinspector-3.2.4.dist-info/WHEEL
lckr_jupyterlab_variableinspector-3.2.4.dist-info/licenses/LICENSE
lckr_jupyterlab_variableinspector-3.2.4.dist-info/RECORD
