Metadata-Version: 2.3
Name: lckr_jupyterlab_variableinspector
Version: 3.2.4
Dynamic: Keywords
Summary: Variable inspector extension for JupyterLab
Project-URL: Homepage, https://github.com/jupyterlab-contrib/jupyterlab-variableInspector
Project-URL: Bug Tracker, https://github.com/jupyterlab-contrib/jupyterlab-variableInspector/issues
Project-URL: Repository, https://github.com/jupyterlab-contrib/jupyterlab-variableInspector.git
Author: lckr
License: BSD 3-Clause License
License-File: LICENSE
Classifier: Framework :: Jupyter
Classifier: Framework :: Jupyter :: JupyterLab
Classifier: Framework :: Jupyter :: JupyterLab :: 4
Classifier: Framework :: Jupyter :: JupyterLab :: Extensions
Classifier: Framework :: Jupyter :: JupyterLab :: Extensions :: Prebuilt
Classifier: License :: OSI Approved :: BSD License
Classifier: Programming Language :: Python
Classifier: Programming Language :: Python :: 3
Classifier: Programming Language :: Python :: 3.8
Classifier: Programming Language :: Python :: 3.9
Classifier: Programming Language :: Python :: 3.10
Classifier: Programming Language :: Python :: 3.11
Classifier: Programming Language :: Python :: 3.12
Requires-Python: >=3.8
